rimc_engine/__init__.py
rimc_engine/convert.py
rimc_engine/convert_temp.py
rimc_engine/effects.py
rimc_engine/recipes.py
rimc_engine/test_allrec.py
rimc_engine/test_allrecipes_plot.py
rimc_engine/test_effects.py
rimc_engine/tools.py
rimc_engine-0.5.2.dist-info/METADATA
rimc_engine-0.5.2.dist-info/WHEEL
rimc_engine-0.5.2.dist-info/licenses/LICENSE
rimc_engine-0.5.2.dist-info/RECORD
