Metadata-Version: 2.3
Name: rimc_engine
Version: 0.5.2
Summary: Film simulation / photo processor python module.
Project-URL: Homepage, https://github.com/bogpok/rimc_engine
Project-URL: Bug Tracker, https://github.com/bogpok/rimc_engine/issues
Author-email: Bogdan Pokrepin <pokrepin@gmail.com>
License-File: LICENSE
Classifier: License :: OSI Approved :: MIT License
Classifier: Operating System :: OS Independent
Classifier: Programming Language :: Python :: 3
Requires-Python: >=3.7
